cimpy/__init__.py
cimpy/cimexamples.py
cimpy/cimexport.py
cimpy/cimimport.py
cimpy/export_template.mustache
cimpy/utils.py
cimpy/cgmes_v2_4_15/ACDCConverter.py
cimpy/cgmes_v2_4_15/ACDCConverterDCTerminal.py
cimpy/cgmes_v2_4_15/ACDCTerminal.py
cimpy/cgmes_v2_4_15/ACLineSegment.py
cimpy/cgmes_v2_4_15/ActivePower.py
cimpy/cgmes_v2_4_15/ActivePowerPerCurrentFlow.py
cimpy/cgmes_v2_4_15/ActivePowerPerFrequency.py
cimpy/cgmes_v2_4_15/AngleDegrees.py
cimpy/cgmes_v2_4_15/AngleRadians.py
cimpy/cgmes_v2_4_15/ApparentPower.py
cimpy/cgmes_v2_4_15/Area.py
cimpy/cgmes_v2_4_15/AsynchronousMachine.py
cimpy/cgmes_v2_4_15/AsynchronousMachineDynamics.py
cimpy/cgmes_v2_4_15/AsynchronousMachineEquivalentCircuit.py
cimpy/cgmes_v2_4_15/AsynchronousMachineKind.py
cimpy/cgmes_v2_4_15/AsynchronousMachineTimeConstantReactance.py
cimpy/cgmes_v2_4_15/AsynchronousMachineUserDefined.py
cimpy/cgmes_v2_4_15/Base.py
cimpy/cgmes_v2_4_15/BaseVoltage.py
cimpy/cgmes_v2_4_15/BasicIntervalSchedule.py
cimpy/cgmes_v2_4_15/Boolean.py
cimpy/cgmes_v2_4_15/Breaker.py
cimpy/cgmes_v2_4_15/BusNameMarker.py
cimpy/cgmes_v2_4_15/BusbarSection.py
cimpy/cgmes_v2_4_15/Capacitance.py
cimpy/cgmes_v2_4_15/CapacitancePerLength.py
cimpy/cgmes_v2_4_15/Conductance.py
cimpy/cgmes_v2_4_15/ConductingEquipment.py
cimpy/cgmes_v2_4_15/Conductor.py
cimpy/cgmes_v2_4_15/ConformLoad.py
cimpy/cgmes_v2_4_15/ConformLoadGroup.py
cimpy/cgmes_v2_4_15/ConnectivityNode.py
cimpy/cgmes_v2_4_15/ConnectivityNodeContainer.py
cimpy/cgmes_v2_4_15/Connector.py
cimpy/cgmes_v2_4_15/ControlArea.py
cimpy/cgmes_v2_4_15/ControlAreaGeneratingUnit.py
cimpy/cgmes_v2_4_15/ControlAreaTypeKind.py
cimpy/cgmes_v2_4_15/CoordinateSystem.py
cimpy/cgmes_v2_4_15/CsConverter.py
cimpy/cgmes_v2_4_15/CsOperatingModeKind.py
cimpy/cgmes_v2_4_15/CsPpccControlKind.py
cimpy/cgmes_v2_4_15/Currency.py
cimpy/cgmes_v2_4_15/CurrentFlow.py
cimpy/cgmes_v2_4_15/CurrentLimit.py
cimpy/cgmes_v2_4_15/Curve.py
cimpy/cgmes_v2_4_15/CurveData.py
cimpy/cgmes_v2_4_15/CurveStyle.py
cimpy-1.0.2.dist-info/LICENSE
cimpy-1.0.2.dist-info/METADATA
cimpy-1.0.2.dist-info/WHEEL
cimpy-1.0.2.dist-info/top_level.txt
cimpy-1.0.2.dist-info/RECORD
